generic_chooser/__init__.py
generic_chooser/views.py
generic_chooser/widgets.py
generic_chooser/static/generic_chooser/js/chooser-modal.js
generic_chooser/static/generic_chooser/js/chooser-widget-telepath.js
generic_chooser/static/generic_chooser/js/chooser-widget.js
generic_chooser/static/generic_chooser/js/linked-field-chooser-widget-telepath.js
generic_chooser/static/generic_chooser/js/linked-field-chooser-widget.js
generic_chooser/static/generic_chooser/js/tabs.js
generic_chooser/templates/generic_chooser/_ajax_pagination_nav.html
generic_chooser/templates/generic_chooser/_create_tab.html
generic_chooser/templates/generic_chooser/_listing_tab.html
generic_chooser/templates/generic_chooser/_results.html
generic_chooser/templates/generic_chooser/tabbed_modal.html
generic_chooser/templates/generic_chooser/tabbed_modal_v3.html
generic_chooser/templates/generic_chooser/widgets/chooser.html
generic_chooser/templates/generic_chooser/widgets/icon_new.html
generic_chooser/templates/generic_chooser/widgets/icon_old.html
wagtail_generic_chooser-0.7.dist-info/licenses/LICENSE
wagtail_generic_chooser-0.7.dist-info/METADATA
wagtail_generic_chooser-0.7.dist-info/WHEEL
wagtail_generic_chooser-0.7.dist-info/top_level.txt
wagtail_generic_chooser-0.7.dist-info/RECORD
